[
    {
        "FilterGroup": 0,
        "FilterOperator": "=",
        "FilterValue": "Role",
        "GlobalKey": "DR_GetReciprocalRoleCustom4685",
        "InputFieldName": "Name",
        "InputObjectName": "HealthCloudGA__ReciprocalRole__c",
        "InputObjectQuerySequence": 1,
        "IsDisabled": false,
        "IsRequiredForUpsert": false,
        "IsUpsertKey": false,
        "Name": "DR_GetReciprocalRole",
        "OmniDataTransformationId": {
            "Name": "DR_GetReciprocalRole",
            "VlocityDataPackType": "VlocityMatchingKeyObject",
            "VlocityMatchingRecordSourceKey": "OmniDataTransform/DR_GetReciprocalRole",
            "VlocityRecordSObjectType": "OmniDataTransform"
        },
        "OutputCreationSequence": 0,
        "OutputFieldName": "ReciprocalRole",
        "OutputObjectName": "json",
        "VlocityDataPackType": "SObject",
        "VlocityRecordSObjectType": "OmniDataTransformItem"
    },
    {
        "GlobalKey": "DR_GetReciprocalRoleCustom9640",
        "InputFieldName": "ReciprocalRole:Id",
        "IsDisabled": false,
        "IsRequiredForUpsert": false,
        "IsUpsertKey": false,
        "Name": "DR_GetReciprocalRole",
        "OmniDataTransformationId": {
            "Name": "DR_GetReciprocalRole",
            "VlocityDataPackType": "VlocityMatchingKeyObject",
            "VlocityMatchingRecordSourceKey": "OmniDataTransform/DR_GetReciprocalRole",
            "VlocityRecordSObjectType": "OmniDataTransform"
        },
        "OutputCreationSequence": 1,
        "OutputFieldName": "ReciprocalRoleId",
        "OutputObjectName": "json",
        "VlocityDataPackType": "SObject",
        "VlocityRecordSObjectType": "OmniDataTransformItem"
    },
    {
        "GlobalKey": "DR_GetReciprocalRoleCustom7846",
        "InputFieldName": "ReciprocalRole:Name",
        "IsDisabled": false,
        "IsRequiredForUpsert": false,
        "IsUpsertKey": false,
        "Name": "DR_GetReciprocalRole",
        "OmniDataTransformationId": {
            "Name": "DR_GetReciprocalRole",
            "VlocityDataPackType": "VlocityMatchingKeyObject",
            "VlocityMatchingRecordSourceKey": "OmniDataTransform/DR_GetReciprocalRole",
            "VlocityRecordSObjectType": "OmniDataTransform"
        },
        "OutputCreationSequence": 1,
        "OutputFieldName": "ReciprocalRoleName",
        "OutputObjectName": "json",
        "VlocityDataPackType": "SObject",
        "VlocityRecordSObjectType": "OmniDataTransformItem"
    }
]